{
  "name": "recording_20250619_060204",
  "created_at": "2025-06-19T06:02:12.248457",
  "action_count": 212,
  "actions": [
    {
      "timestamp": 0.19713568687438965,
      "action_type": "mouse_move",
      "data": {
        "x": 445,
        "y": 392
      },
      "delay_after": 0.0
    },
    {
      "timestamp": 0.20456862449645996,
      "action_type": "mouse_move",
      "data": {
        "x": 446,
        "y": 389
      },
      "delay_after": 0.0
    },
    {
      "timestamp": 0.2119436264038086,
      "action_type": "mouse_move",
      "data": {
        "x": 448,
        "y": 386
      },
      "delay_after": 0.0
    },
    {
      "timestamp": 0.21898460388183594,
      "action_type": "mouse_move",
      "data": {
        "x": 449,
        "y": 384
      },
      "delay_after": 0.0
    },
    {
      "timestamp": 0.22696757316589355,
      "action_type": "mouse_move",
      "data": {
        "x": 453,
        "y": 382
      },
      "delay_after": 0.0
    },
    {
      "timestamp": 0.2342369556427002,
      "action_type": "mouse_move",
      "data": {
        "x": 456,
        "y": 380
      },
      "delay_after": 0.0
    },
    {
      "timestamp": 0.2415482997894287,
      "action_type": "mouse_move",
      "data": {
        "x": 457,
        "y": 380
      },
      "delay_after": 0.0
    },
    {
      "timestamp": 0.24920177459716797,
      "action_type": "mouse_move",
      "data": {
        "x": 459,
        "y": 380
      },
      "delay_after": 0.0
    },
    {
      "timestamp": 0.2567026615142822,
      "action_type": "mouse_move",
      "data": {
        "x": 460,
        "y": 380
      },
      "delay_after": 0.0
    },
    {
      "timestamp": 1.622107982635498,
      "action_type": "mouse_move",
      "data": {
        "x": 461,
        "y": 380
      },
      "delay_after": 0.0
    },
    {
      "timestamp": 1.6289801597595215,
      "action_type": "mouse_move",
      "data": {
        "x": 467,
        "y": 380
      },
      "delay_after": 0.0
    },
    {
      "timestamp": 1.636995553970337,
      "action_type": "mouse_move",
      "data": {
        "x": 472,
        "y": 380
      },
      "delay_after": 0.0
    },
    {
      "timestamp": 1.644029140472412,
      "action_type": "mouse_move",
      "data": {
        "x": 481,
        "y": 380
      },
      "delay_after": 0.0
    },
    {
      "timestamp": 1.6514992713928223,
      "action_type": "mouse_move",
      "data": {
        "x": 497,
        "y": 380
      },
      "delay_after": 0.0
    },
    {
      "timestamp": 1.6589291095733643,
      "action_type": "mouse_move",
      "data": {
        "x": 519,
        "y": 379
      },
      "delay_after": 0.0
    },
    {
      "timestamp": 1.666579008102417,
      "action_type": "mouse_move",
      "data": {
        "x": 553,
        "y": 377
      },
      "delay_after": 0.0
    },
    {
      "timestamp": 1.6738917827606201,
      "action_type": "mouse_move",
      "data": {
        "x": 603,
        "y": 372
      },
      "delay_after": 0.0
    },
    {
      "timestamp": 1.681826114654541,
      "action_type": "mouse_move",
      "data": {
        "x": 674,
        "y": 363
      },
      "delay_after": 0.0
    },
    {
      "timestamp": 1.6891469955444336,
      "action_type": "mouse_move",
      "data": {
        "x": 761,
        "y": 354
      },
      "delay_after": 0.0
    },
    {
      "timestamp": 1.696716547012329,
      "action_type": "mouse_move",
      "data": {
        "x": 872,
        "y": 342
      },
      "delay_after": 0.0
    },
    {
      "timestamp": 1.7046172618865967,
      "action_type": "mouse_move",
      "data": {
        "x": 991,
        "y": 325
      },
      "delay_after": 0.0
    },
    {
      "timestamp": 1.711395263671875,
      "action_type": "mouse_move",
      "data": {
        "x": 1135,
        "y": 302
      },
      "delay_after": 0.0
    },
    {
      "timestamp": 1.7192480564117432,
      "action_type": "mouse_move",
      "data": {
        "x": 1271,
        "y": 279
      },
      "delay_after": 0.0
    },
    {
      "timestamp": 1.7268803119659424,
      "action_type": "mouse_move",
      "data": {
        "x": 1416,
        "y": 252
      },
      "delay_after": 0.0
    },
    {
      "timestamp": 1.7340545654296875,
      "action_type": "mouse_move",
      "data": {
        "x": 1552,
        "y": 229
      },
      "delay_after": 0.0
    },
    {
      "timestamp": 1.741265058517456,
      "action_type": "mouse_move",
      "data": {
        "x": 1684,
        "y": 206
      },
      "delay_after": 0.0
    },
    {
      "timestamp": 1.7487213611602783,
      "action_type": "mouse_move",
      "data": {
        "x": 1787,
        "y": 190
      },
      "delay_after": 0.0
    },
    {
      "timestamp": 1.7563037872314453,
      "action_type": "mouse_move",
      "data": {
        "x": 1882,
        "y": 181
      },
      "delay_after": 0.0
    },
    {
      "timestamp": 1.7638695240020752,
      "action_type": "mouse_move",
      "data": {
        "x": 1952,
        "y": 175
      },
      "delay_after": 0.0
    },
    {
      "timestamp": 1.7712254524230957,
      "action_type": "mouse_move",
      "data": {
        "x": 1965,
        "y": 173
      },
      "delay_after": 0.0
    },
    {
      "timestamp": 1.7787983417510986,
      "action_type": "mouse_move",
      "data": {
        "x": 1941,
        "y": 171
      },
      "delay_after": 0.0
    },
    {
      "timestamp": 1.78652024269104,
      "action_type": "mouse_move",
      "data": {
        "x": 1921,
        "y": 171
      },
      "delay_after": 0.0
    },
    {
      "timestamp": 1.8535823822021484,
      "action_type": "mouse_move",
      "data": {
        "x": 1921,
        "y": 171
      },
      "delay_after": 0.0
    },
    {
      "timestamp": 1.8611106872558594,
      "action_type": "mouse_move",
      "data": {
        "x": 1920,
        "y": 171
      },
      "delay_after": 0.0
    },
    {
      "timestamp": 1.9589085578918457,
      "action_type": "mouse_move",
      "data": {
        "x": 1918,
        "y": 171
      },
      "delay_after": 0.0
    },
    {
      "timestamp": 1.9662320613861084,
      "action_type": "mouse_move",
      "data": {
        "x": 1917,
        "y": 171
      },
      "delay_after": 0.0
    },
    {
      "timestamp": 1.9737756252288818,
      "action_type": "mouse_move",
      "data": {
        "x": 1914,
        "y": 171
      },
      "delay_after": 0.0
    },
    {
      "timestamp": 1.9813461303710938,
      "action_type": "mouse_move",
      "data": {
        "x": 1906,
        "y": 171
      },
      "delay_after": 0.0
    },
    {
      "timestamp": 1.9886419773101807,
      "action_type": "mouse_move",
      "data": {
        "x": 1902,
        "y": 171
      },
      "delay_after": 0.0
    },
    {
      "timestamp": 1.996556043624878,
      "action_type": "mouse_move",
      "data": {
        "x": 1897,
        "y": 171
      },
      "delay_after": 0.0
    },
    {
      "timestamp": 2.0042307376861572,
      "action_type": "mouse_move",
      "data": {
        "x": 1893,
        "y": 171
      },
      "delay_after": 0.0
    },
    {
      "timestamp": 2.0115230083465576,
      "action_type": "mouse_move",
      "data": {
        "x": 1888,
        "y": 171
      },
      "delay_after": 0.0
    },
    {
      "timestamp": 2.0191166400909424,
      "action_type": "mouse_move",
      "data": {
        "x": 1881,
        "y": 171
      },
      "delay_after": 0.0
    },
    {
      "timestamp": 2.0264785289764404,
      "action_type": "mouse_move",
      "data": {
        "x": 1873,
        "y": 171
      },
      "delay_after": 0.0
    },
    {
      "timestamp": 2.0339972972869873,
      "action_type": "mouse_move",
      "data": {
        "x": 1863,
        "y": 171
      },
      "delay_after": 0.0
    },
    {
      "timestamp": 2.041456699371338,
      "action_type": "mouse_move",
      "data": {
        "x": 1851,
        "y": 171
      },
      "delay_after": 0.0
    },
    {
      "timestamp": 2.0489678382873535,
      "action_type": "mouse_move",
      "data": {
        "x": 1841,
        "y": 171
      },
      "delay_after": 0.0
    },
    {
      "timestamp": 2.0561611652374268,
      "action_type": "mouse_move",
      "data": {
        "x": 1837,
        "y": 171
      },
      "delay_after": 0.0
    },
    {
      "timestamp": 2.06392240524292,
      "action_type": "mouse_move",
      "data": {
        "x": 1833,
        "y": 171
      },
      "delay_after": 0.0
    },
    {
      "timestamp": 2.0713539123535156,
      "action_type": "mouse_move",
      "data": {
        "x": 1827,
        "y": 172
      },
      "delay_after": 0.0
    },
    {
      "timestamp": 2.079349994659424,
      "action_type": "mouse_move",
      "data": {
        "x": 1822,
        "y": 172
      },
      "delay_after": 0.0
    },
    {
      "timestamp": 2.0863020420074463,
      "action_type": "mouse_move",
      "data": {
        "x": 1817,
        "y": 173
      },
      "delay_after": 0.0
    },
    {
      "timestamp": 2.0939137935638428,
      "action_type": "mouse_move",
      "data": {
        "x": 1814,
        "y": 173
      },
      "delay_after": 0.0
    },
    {
      "timestamp": 2.1013548374176025,
      "action_type": "mouse_move",
      "data": {
        "x": 1811,
        "y": 175
      },
      "delay_after": 0.0
    },
    {
      "timestamp": 2.1090452671051025,
      "action_type": "mouse_move",
      "data": {
        "x": 1807,
        "y": 175
      },
      "delay_after": 0.0
    },
    {
      "timestamp": 2.11674427986145,
      "action_type": "mouse_move",
      "data": {
        "x": 1805,
        "y": 175
      },
      "delay_after": 0.0
    },
    {
      "timestamp": 2.1242854595184326,
      "action_type": "mouse_move",
      "data": {
        "x": 1801,
        "y": 176
      },
      "delay_after": 0.0
    },
    {
      "timestamp": 2.131991386413574,
      "action_type": "mouse_move",
      "data": {
        "x": 1798,
        "y": 177
      },
      "delay_after": 0.0
    },
    {
      "timestamp": 2.139089584350586,
      "action_type": "mouse_move",
      "data": {
        "x": 1795,
        "y": 178
      },
      "delay_after": 0.0
    },
    {
      "timestamp": 2.146707773208618,
      "action_type": "mouse_move",
      "data": {
        "x": 1791,
        "y": 178
      },
      "delay_after": 0.0
    },
    {
      "timestamp": 2.161663770675659,
      "action_type": "mouse_move",
      "data": {
        "x": 1788,
        "y": 178
      },
      "delay_after": 0.0
    },
    {
      "timestamp": 2.1641628742218018,
      "action_type": "mouse_move",
      "data": {
        "x": 1786,
        "y": 179
      },
      "delay_after": 0.0
    },
    {
      "timestamp": 2.170177936553955,
      "action_type": "mouse_move",
      "data": {
        "x": 1785,
        "y": 179
      },
      "delay_after": 0.0
    },
    {
      "timestamp": 2.2591428756713867,
      "action_type": "mouse_move",
      "data": {
        "x": 1785,
        "y": 179
      },
      "delay_after": 0.0
    },
    {
      "timestamp": 2.402078151702881,
      "action_type": "mouse_move",
      "data": {
        "x": 1784,
        "y": 179
      },
      "delay_after": 0.0
    },
    {
      "timestamp": 2.409562349319458,
      "action_type": "mouse_move",
      "data": {
        "x": 1777,
        "y": 179
      },
      "delay_after": 0.0
    },
    {
      "timestamp": 2.4168641567230225,
      "action_type": "mouse_move",
      "data": {
        "x": 1771,
        "y": 179
      },
      "delay_after": 0.0
    },
    {
      "timestamp": 2.4245290756225586,
      "action_type": "mouse_move",
      "data": {
        "x": 1767,
        "y": 180
      },
      "delay_after": 0.0
    },
    {
      "timestamp": 2.431485891342163,
      "action_type": "mouse_move",
      "data": {
        "x": 1762,
        "y": 180
      },
      "delay_after": 0.0
    },
    {
      "timestamp": 2.438647508621216,
      "action_type": "mouse_move",
      "data": {
        "x": 1758,
        "y": 180
      },
      "delay_after": 0.0
    },
    {
      "timestamp": 2.446687698364258,
      "action_type": "mouse_move",
      "data": {
        "x": 1754,
        "y": 180
      },
      "delay_after": 0.0
    },
    {
      "timestamp": 2.4542365074157715,
      "action_type": "mouse_move",
      "data": {
        "x": 1750,
        "y": 180
      },
      "delay_after": 0.0
    },
    {
      "timestamp": 2.4618172645568848,
      "action_type": "mouse_move",
      "data": {
        "x": 1749,
        "y": 180
      },
      "delay_after": 0.0
    },
    {
      "timestamp": 2.4694385528564453,
      "action_type": "mouse_move",
      "data": {
        "x": 1747,
        "y": 180
      },
      "delay_after": 0.0
    },
    {
      "timestamp": 2.476907253265381,
      "action_type": "mouse_move",
      "data": {
        "x": 1746,
        "y": 180
      },
      "delay_after": 0.0
    },
    {
      "timestamp": 2.491644859313965,
      "action_type": "mouse_move",
      "data": {
        "x": 1746,
        "y": 180
      },
      "delay_after": 0.0
    },
    {
      "timestamp": 2.514434337615967,
      "action_type": "mouse_move",
      "data": {
        "x": 1745,
        "y": 180
      },
      "delay_after": 0.0
    },
    {
      "timestamp": 2.5288994312286377,
      "action_type": "mouse_move",
      "data": {
        "x": 1744,
        "y": 180
      },
      "delay_after": 0.0
    },
    {
      "timestamp": 2.536170721054077,
      "action_type": "mouse_move",
      "data": {
        "x": 1743,
        "y": 180
      },
      "delay_after": 0.0
    },
    {
      "timestamp": 2.543596029281616,
      "action_type": "mouse_move",
      "data": {
        "x": 1742,
        "y": 180
      },
      "delay_after": 0.0
    },
    {
      "timestamp": 2.5510730743408203,
      "action_type": "mouse_move",
      "data": {
        "x": 1741,
        "y": 180
      },
      "delay_after": 0.0
    },
    {
      "timestamp": 2.5585131645202637,
      "action_type": "mouse_move",
      "data": {
        "x": 1739,
        "y": 181
      },
      "delay_after": 0.0
    },
    {
      "timestamp": 2.573312997817993,
      "action_type": "mouse_move",
      "data": {
        "x": 1739,
        "y": 182
      },
      "delay_after": 0.0
    },
    {
      "timestamp": 2.5813679695129395,
      "action_type": "mouse_move",
      "data": {
        "x": 1738,
        "y": 182
      },
      "delay_after": 0.0
    },
    {
      "timestamp": 2.596163749694824,
      "action_type": "mouse_move",
      "data": {
        "x": 1737,
        "y": 182
      },
      "delay_after": 0.0
    },
    {
      "timestamp": 2.6336045265197754,
      "action_type": "mouse_move",
      "data": {
        "x": 1736,
        "y": 182
      },
      "delay_after": 0.0
    },
    {
      "timestamp": 4.171864748001099,
      "action_type": "mouse_move",
      "data": {
        "x": 1735,
        "y": 183
      },
      "delay_after": 0.0
    },
    {
      "timestamp": 4.174485206604004,
      "action_type": "mouse_move",
      "data": {
        "x": 1734,
        "y": 184
      },
      "delay_after": 0.0
    },
    {
      "timestamp": 4.179187536239624,
      "action_type": "mouse_move",
      "data": {
        "x": 1729,
        "y": 185
      },
      "delay_after": 0.0
    },
    {
      "timestamp": 4.186833381652832,
      "action_type": "mouse_move",
      "data": {
        "x": 1728,
        "y": 185
      },
      "delay_after": 0.0
    },
    {
      "timestamp": 4.194108486175537,
      "action_type": "mouse_move",
      "data": {
        "x": 1727,
        "y": 186
      },
      "delay_after": 0.0
    },
    {
      "timestamp": 5.933854579925537,
      "action_type": "mouse_move",
      "data": {
        "x": 1727,
        "y": 185
      },
      "delay_after": 0.0
    },
    {
      "timestamp": 5.934597730636597,
      "action_type": "mouse_move",
      "data": {
        "x": 1726,
        "y": 184
      },
      "delay_after": 0.0
    },
    {
      "timestamp": 5.94162654876709,
      "action_type": "mouse_move",
      "data": {
        "x": 1725,
        "y": 179
      },
      "delay_after": 0.0
    },
    {
      "timestamp": 5.949350833892822,
      "action_type": "mouse_move",
      "data": {
        "x": 1724,
        "y": 170
      },
      "delay_after": 0.0
    },
    {
      "timestamp": 5.956387996673584,
      "action_type": "mouse_move",
      "data": {
        "x": 1722,
        "y": 162
      },
      "delay_after": 0.0
    },
    {
      "timestamp": 5.964276313781738,
      "action_type": "mouse_move",
      "data": {
        "x": 1721,
        "y": 159
      },
      "delay_after": 0.0
    },
    {
      "timestamp": 5.971831798553467,
      "action_type": "mouse_move",
      "data": {
        "x": 1721,
        "y": 153
      },
      "delay_after": 0.0
    },
    {
      "timestamp": 5.9791483879089355,
      "action_type": "mouse_move",
      "data": {
        "x": 1720,
        "y": 146
      },
      "delay_after": 0.0
    },
    {
      "timestamp": 5.98676609992981,
      "action_type": "mouse_move",
      "data": {
        "x": 1716,
        "y": 137
      },
      "delay_after": 0.0
    },
    {
      "timestamp": 5.994203567504883,
      "action_type": "mouse_move",
      "data": {
        "x": 1711,
        "y": 130
      },
      "delay_after": 0.0
    },
    {
      "timestamp": 6.001943349838257,
      "action_type": "mouse_move",
      "data": {
        "x": 1707,
        "y": 123
      },
      "delay_after": 0.0
    },
    {
      "timestamp": 6.0095131397247314,
      "action_type": "mouse_move",
      "data": {
        "x": 1704,
        "y": 117
      },
      "delay_after": 0.0
    },
    {
      "timestamp": 6.01691746711731,
      "action_type": "mouse_move",
      "data": {
        "x": 1702,
        "y": 113
      },
      "delay_after": 0.0
    },
    {
      "timestamp": 6.024799823760986,
      "action_type": "mouse_move",
      "data": {
        "x": 1700,
        "y": 108
      },
      "delay_after": 0.0
    },
    {
      "timestamp": 6.032068490982056,
      "action_type": "mouse_move",
      "data": {
        "x": 1699,
        "y": 106
      },
      "delay_after": 0.0
    },
    {
      "timestamp": 6.039962530136108,
      "action_type": "mouse_move",
      "data": {
        "x": 1699,
        "y": 104
      },
      "delay_after": 0.0
    },
    {
      "timestamp": 6.046827077865601,
      "action_type": "mouse_move",
      "data": {
        "x": 1699,
        "y": 102
      },
      "delay_after": 0.0
    },
    {
      "timestamp": 6.05477237701416,
      "action_type": "mouse_move",
      "data": {
        "x": 1699,
        "y": 101
      },
      "delay_after": 0.0
    },
    {
      "timestamp": 6.062294006347656,
      "action_type": "mouse_move",
      "data": {
        "x": 1699,
        "y": 100
      },
      "delay_after": 0.0
    },
    {
      "timestamp": 6.0694310665130615,
      "action_type": "mouse_move",
      "data": {
        "x": 1699,
        "y": 99
      },
      "delay_after": 0.0
    },
    {
      "timestamp": 6.076955080032349,
      "action_type": "mouse_move",
      "data": {
        "x": 1700,
        "y": 98
      },
      "delay_after": 0.0
    },
    {
      "timestamp": 6.084991455078125,
      "action_type": "mouse_move",
      "data": {
        "x": 1700,
        "y": 97
      },
      "delay_after": 0.0
    },
    {
      "timestamp": 6.092007398605347,
      "action_type": "mouse_move",
      "data": {
        "x": 1700,
        "y": 96
      },
      "delay_after": 0.0
    },
    {
      "timestamp": 6.098971366882324,
      "action_type": "mouse_move",
      "data": {
        "x": 1701,
        "y": 95
      },
      "delay_after": 0.0
    },
    {
      "timestamp": 6.106410503387451,
      "action_type": "mouse_move",
      "data": {
        "x": 1701,
        "y": 94
      },
      "delay_after": 0.0
    },
    {
      "timestamp": 6.113849639892578,
      "action_type": "mouse_move",
      "data": {
        "x": 1702,
        "y": 93
      },
      "delay_after": 0.0
    },
    {
      "timestamp": 6.2264015674591064,
      "action_type": "mouse_move",
      "data": {
        "x": 1702,
        "y": 91
      },
      "delay_after": 0.0
    },
    {
      "timestamp": 6.233763694763184,
      "action_type": "mouse_move",
      "data": {
        "x": 1702,
        "y": 90
      },
      "delay_after": 0.0
    },
    {
      "timestamp": 6.24216103553772,
      "action_type": "mouse_move",
      "data": {
        "x": 1702,
        "y": 89
      },
      "delay_after": 0.0
    },
    {
      "timestamp": 6.257006406784058,
      "action_type": "mouse_move",
      "data": {
        "x": 1702,
        "y": 88
      },
      "delay_after": 0.0
    },
    {
      "timestamp": 6.279343366622925,
      "action_type": "mouse_move",
      "data": {
        "x": 1702,
        "y": 88
      },
      "delay_after": 0.0
    },
    {
      "timestamp": 6.3016767501831055,
      "action_type": "mouse_move",
      "data": {
        "x": 1702,
        "y": 87
      },
      "delay_after": 0.0
    },
    {
      "timestamp": 6.317831754684448,
      "action_type": "mouse_move",
      "data": {
        "x": 1702,
        "y": 85
      },
      "delay_after": 0.0
    },
    {
      "timestamp": 6.3244383335113525,
      "action_type": "mouse_move",
      "data": {
        "x": 1702,
        "y": 84
      },
      "delay_after": 0.0
    },
    {
      "timestamp": 6.331632137298584,
      "action_type": "mouse_move",
      "data": {
        "x": 1702,
        "y": 83
      },
      "delay_after": 0.0
    },
    {
      "timestamp": 6.339564561843872,
      "action_type": "mouse_move",
      "data": {
        "x": 1702,
        "y": 81
      },
      "delay_after": 0.0
    },
    {
      "timestamp": 6.3467230796813965,
      "action_type": "mouse_move",
      "data": {
        "x": 1702,
        "y": 80
      },
      "delay_after": 0.0
    },
    {
      "timestamp": 6.353863716125488,
      "action_type": "mouse_move",
      "data": {
        "x": 1702,
        "y": 80
      },
      "delay_after": 0.0
    },
    {
      "timestamp": 6.361780881881714,
      "action_type": "mouse_move",
      "data": {
        "x": 1702,
        "y": 79
      },
      "delay_after": 0.0
    },
    {
      "timestamp": 6.369400978088379,
      "action_type": "mouse_move",
      "data": {
        "x": 1702,
        "y": 78
      },
      "delay_after": 0.0
    },
    {
      "timestamp": 6.37675929069519,
      "action_type": "mouse_move",
      "data": {
        "x": 1702,
        "y": 77
      },
      "delay_after": 0.0
    },
    {
      "timestamp": 6.392040967941284,
      "action_type": "mouse_move",
      "data": {
        "x": 1701,
        "y": 76
      },
      "delay_after": 0.0
    },
    {
      "timestamp": 6.399383544921875,
      "action_type": "mouse_move",
      "data": {
        "x": 1701,
        "y": 75
      },
      "delay_after": 0.0
    },
    {
      "timestamp": 6.421564817428589,
      "action_type": "mouse_move",
      "data": {
        "x": 1701,
        "y": 75
      },
      "delay_after": 0.0
    },
    {
      "timestamp": 6.473853588104248,
      "action_type": "mouse_move",
      "data": {
        "x": 1701,
        "y": 74
      },
      "delay_after": 0.0
    },
    {
      "timestamp": 6.526271343231201,
      "action_type": "mouse_move",
      "data": {
        "x": 1701,
        "y": 73
      },
      "delay_after": 0.0
    },
    {
      "timestamp": 6.533630132675171,
      "action_type": "mouse_move",
      "data": {
        "x": 1701,
        "y": 72
      },
      "delay_after": 0.0
    },
    {
      "timestamp": 6.548587799072266,
      "action_type": "mouse_move",
      "data": {
        "x": 1701,
        "y": 71
      },
      "delay_after": 0.0
    },
    {
      "timestamp": 6.563601970672607,
      "action_type": "mouse_move",
      "data": {
        "x": 1701,
        "y": 70
      },
      "delay_after": 0.0
    },
    {
      "timestamp": 6.578580141067505,
      "action_type": "mouse_move",
      "data": {
        "x": 1701,
        "y": 69
      },
      "delay_after": 0.0
    },
    {
      "timestamp": 6.593461036682129,
      "action_type": "mouse_move",
      "data": {
        "x": 1701,
        "y": 69
      },
      "delay_after": 0.0
    },
    {
      "timestamp": 6.601044416427612,
      "action_type": "mouse_move",
      "data": {
        "x": 1701,
        "y": 68
      },
      "delay_after": 0.0
    },
    {
      "timestamp": 6.608393430709839,
      "action_type": "mouse_move",
      "data": {
        "x": 1701,
        "y": 67
      },
      "delay_after": 0.0
    },
    {
      "timestamp": 6.616153240203857,
      "action_type": "mouse_move",
      "data": {
        "x": 1701,
        "y": 66
      },
      "delay_after": 0.0
    },
    {
      "timestamp": 6.623492956161499,
      "action_type": "mouse_move",
      "data": {
        "x": 1701,
        "y": 65
      },
      "delay_after": 0.0
    },
    {
      "timestamp": 6.698768854141235,
      "action_type": "mouse_move",
      "data": {
        "x": 1701,
        "y": 64
      },
      "delay_after": 0.0
    },
    {
      "timestamp": 6.736175060272217,
      "action_type": "mouse_move",
      "data": {
        "x": 1701,
        "y": 63
      },
      "delay_after": 0.0
    },
    {
      "timestamp": 6.773550987243652,
      "action_type": "mouse_click",
      "data": {
        "x": 1701,
        "y": 63,
        "button": "Button.left",
        "pressed": true
      },
      "delay_after": 0.0
    },
    {
      "timestamp": 6.825892210006714,
      "action_type": "mouse_move",
      "data": {
        "x": 1700,
        "y": 63
      },
      "delay_after": 0.0
    },
    {
      "timestamp": 6.84093165397644,
      "action_type": "mouse_move",
      "data": {
        "x": 1696,
        "y": 63
      },
      "delay_after": 0.0
    },
    {
      "timestamp": 6.848459720611572,
      "action_type": "mouse_move",
      "data": {
        "x": 1690,
        "y": 64
      },
      "delay_after": 0.0
    },
    {
      "timestamp": 6.856050491333008,
      "action_type": "mouse_move",
      "data": {
        "x": 1686,
        "y": 65
      },
      "delay_after": 0.0
    },
    {
      "timestamp": 6.8634889125823975,
      "action_type": "mouse_move",
      "data": {
        "x": 1679,
        "y": 66
      },
      "delay_after": 0.0
    },
    {
      "timestamp": 6.870985269546509,
      "action_type": "mouse_move",
      "data": {
        "x": 1668,
        "y": 69
      },
      "delay_after": 0.0
    },
    {
      "timestamp": 6.878577709197998,
      "action_type": "mouse_move",
      "data": {
        "x": 1656,
        "y": 72
      },
      "delay_after": 0.0
    },
    {
      "timestamp": 6.886011600494385,
      "action_type": "mouse_move",
      "data": {
        "x": 1639,
        "y": 79
      },
      "delay_after": 0.0
    },
    {
      "timestamp": 6.893773078918457,
      "action_type": "mouse_move",
      "data": {
        "x": 1623,
        "y": 84
      },
      "delay_after": 0.0
    },
    {
      "timestamp": 6.901505947113037,
      "action_type": "mouse_move",
      "data": {
        "x": 1606,
        "y": 89
      },
      "delay_after": 0.0
    },
    {
      "timestamp": 6.90861177444458,
      "action_type": "mouse_move",
      "data": {
        "x": 1585,
        "y": 96
      },
      "delay_after": 0.0
    },
    {
      "timestamp": 6.916213274002075,
      "action_type": "mouse_move",
      "data": {
        "x": 1571,
        "y": 100
      },
      "delay_after": 0.0
    },
    {
      "timestamp": 6.923458099365234,
      "action_type": "mouse_move",
      "data": {
        "x": 1557,
        "y": 104
      },
      "delay_after": 0.0
    },
    {
      "timestamp": 6.9311277866363525,
      "action_type": "mouse_move",
      "data": {
        "x": 1546,
        "y": 107
      },
      "delay_after": 0.0
    },
    {
      "timestamp": 6.93882155418396,
      "action_type": "mouse_move",
      "data": {
        "x": 1538,
        "y": 108
      },
      "delay_after": 0.0
    },
    {
      "timestamp": 6.946077585220337,
      "action_type": "mouse_move",
      "data": {
        "x": 1531,
        "y": 111
      },
      "delay_after": 0.0
    },
    {
      "timestamp": 6.9535722732543945,
      "action_type": "mouse_move",
      "data": {
        "x": 1526,
        "y": 112
      },
      "delay_after": 0.0
    },
    {
      "timestamp": 6.960972785949707,
      "action_type": "mouse_move",
      "data": {
        "x": 1523,
        "y": 113
      },
      "delay_after": 0.0
    },
    {
      "timestamp": 6.9689788818359375,
      "action_type": "mouse_move",
      "data": {
        "x": 1520,
        "y": 114
      },
      "delay_after": 0.0
    },
    {
      "timestamp": 6.976156711578369,
      "action_type": "mouse_move",
      "data": {
        "x": 1518,
        "y": 115
      },
      "delay_after": 0.0
    },
    {
      "timestamp": 6.983594655990601,
      "action_type": "mouse_move",
      "data": {
        "x": 1511,
        "y": 118
      },
      "delay_after": 0.0
    },
    {
      "timestamp": 6.991517543792725,
      "action_type": "mouse_move",
      "data": {
        "x": 1504,
        "y": 120
      },
      "delay_after": 0.0
    },
    {
      "timestamp": 6.998860120773315,
      "action_type": "mouse_move",
      "data": {
        "x": 1500,
        "y": 123
      },
      "delay_after": 0.0
    },
    {
      "timestamp": 7.006166696548462,
      "action_type": "mouse_move",
      "data": {
        "x": 1496,
        "y": 125
      },
      "delay_after": 0.0
    },
    {
      "timestamp": 7.014220237731934,
      "action_type": "mouse_move",
      "data": {
        "x": 1493,
        "y": 127
      },
      "delay_after": 0.0
    },
    {
      "timestamp": 7.0216100215911865,
      "action_type": "mouse_move",
      "data": {
        "x": 1490,
        "y": 128
      },
      "delay_after": 0.0
    },
    {
      "timestamp": 7.02901291847229,
      "action_type": "mouse_move",
      "data": {
        "x": 1487,
        "y": 131
      },
      "delay_after": 0.0
    },
    {
      "timestamp": 7.036007642745972,
      "action_type": "mouse_move",
      "data": {
        "x": 1487,
        "y": 131
      },
      "delay_after": 0.0
    },
    {
      "timestamp": 7.043731689453125,
      "action_type": "mouse_move",
      "data": {
        "x": 1486,
        "y": 131
      },
      "delay_after": 0.0
    },
    {
      "timestamp": 7.0509934425354,
      "action_type": "mouse_move",
      "data": {
        "x": 1485,
        "y": 132
      },
      "delay_after": 0.0
    },
    {
      "timestamp": 7.0584962368011475,
      "action_type": "mouse_move",
      "data": {
        "x": 1484,
        "y": 133
      },
      "delay_after": 0.0
    },
    {
      "timestamp": 7.073733806610107,
      "action_type": "mouse_move",
      "data": {
        "x": 1483,
        "y": 133
      },
      "delay_after": 0.0
    },
    {
      "timestamp": 7.15727972984314,
      "action_type": "mouse_click",
      "data": {
        "x": 1483,
        "y": 133,
        "button": "Button.left",
        "pressed": false
      },
      "delay_after": 0.0
    },
    {
      "timestamp": 7.186548948287964,
      "action_type": "mouse_move",
      "data": {
        "x": 1487,
        "y": 137
      },
      "delay_after": 0.0
    },
    {
      "timestamp": 7.19486403465271,
      "action_type": "mouse_move",
      "data": {
        "x": 1489,
        "y": 140
      },
      "delay_after": 0.0
    },
    {
      "timestamp": 7.202090263366699,
      "action_type": "mouse_move",
      "data": {
        "x": 1491,
        "y": 143
      },
      "delay_after": 0.0
    },
    {
      "timestamp": 7.210299968719482,
      "action_type": "mouse_move",
      "data": {
        "x": 1493,
        "y": 145
      },
      "delay_after": 0.0
    },
    {
      "timestamp": 7.217343330383301,
      "action_type": "mouse_move",
      "data": {
        "x": 1496,
        "y": 149
      },
      "delay_after": 0.0
    },
    {
      "timestamp": 7.224867582321167,
      "action_type": "mouse_move",
      "data": {
        "x": 1503,
        "y": 153
      },
      "delay_after": 0.0
    },
    {
      "timestamp": 7.233467102050781,
      "action_type": "mouse_move",
      "data": {
        "x": 1506,
        "y": 156
      },
      "delay_after": 0.0
    },
    {
      "timestamp": 7.2398152351379395,
      "action_type": "mouse_move",
      "data": {
        "x": 1508,
        "y": 158
      },
      "delay_after": 0.0
    },
    {
      "timestamp": 7.248201131820679,
      "action_type": "mouse_move",
      "data": {
        "x": 1509,
        "y": 162
      },
      "delay_after": 0.0
    },
    {
      "timestamp": 7.254688501358032,
      "action_type": "mouse_move",
      "data": {
        "x": 1511,
        "y": 166
      },
      "delay_after": 0.0
    },
    {
      "timestamp": 7.2623138427734375,
      "action_type": "mouse_move",
      "data": {
        "x": 1512,
        "y": 170
      },
      "delay_after": 0.0
    },
    {
      "timestamp": 7.2695631980896,
      "action_type": "mouse_move",
      "data": {
        "x": 1514,
        "y": 173
      },
      "delay_after": 0.0
    },
    {
      "timestamp": 7.276833534240723,
      "action_type": "mouse_move",
      "data": {
        "x": 1515,
        "y": 178
      },
      "delay_after": 0.0
    },
    {
      "timestamp": 7.28449559211731,
      "action_type": "mouse_move",
      "data": {
        "x": 1515,
        "y": 184
      },
      "delay_after": 0.0
    },
    {
      "timestamp": 7.29154109954834,
      "action_type": "mouse_move",
      "data": {
        "x": 1516,
        "y": 192
      },
      "delay_after": 0.0
    },
    {
      "timestamp": 7.300273180007935,
      "action_type": "mouse_move",
      "data": {
        "x": 1517,
        "y": 195
      },
      "delay_after": 0.0
    },
    {
      "timestamp": 7.30672025680542,
      "action_type": "mouse_move",
      "data": {
        "x": 1520,
        "y": 202
      },
      "delay_after": 0.0
    },
    {
      "timestamp": 7.3155999183654785,
      "action_type": "mouse_move",
      "data": {
        "x": 1521,
        "y": 206
      },
      "delay_after": 0.0
    },
    {
      "timestamp": 7.3221352100372314,
      "action_type": "mouse_move",
      "data": {
        "x": 1522,
        "y": 211
      },
      "delay_after": 0.0
    },
    {
      "timestamp": 7.329709768295288,
      "action_type": "mouse_move",
      "data": {
        "x": 1523,
        "y": 218
      },
      "delay_after": 0.0
    },
    {
      "timestamp": 7.337061643600464,
      "action_type": "mouse_move",
      "data": {
        "x": 1526,
        "y": 226
      },
      "delay_after": 0.0
    },
    {
      "timestamp": 7.344330549240112,
      "action_type": "mouse_move",
      "data": {
        "x": 1528,
        "y": 237
      },
      "delay_after": 0.0
    },
    {
      "timestamp": 7.351940393447876,
      "action_type": "mouse_move",
      "data": {
        "x": 1529,
        "y": 245
      },
      "delay_after": 0.0
    },
    {
      "timestamp": 7.359016418457031,
      "action_type": "mouse_move",
      "data": {
        "x": 1530,
        "y": 251
      },
      "delay_after": 0.0
    },
    {
      "timestamp": 7.3667192459106445,
      "action_type": "mouse_move",
      "data": {
        "x": 1532,
        "y": 258
      },
      "delay_after": 0.0
    },
    {
      "timestamp": 7.374238729476929,
      "action_type": "mouse_move",
      "data": {
        "x": 1533,
        "y": 264
      },
      "delay_after": 0.0
    },
    {
      "timestamp": 7.381983280181885,
      "action_type": "mouse_move",
      "data": {
        "x": 1533,
        "y": 268
      },
      "delay_after": 0.0
    },
    {
      "timestamp": 7.389369249343872,
      "action_type": "mouse_move",
      "data": {
        "x": 1533,
        "y": 270
      },
      "delay_after": 0.0
    },
    {
      "timestamp": 7.831396102905273,
      "action_type": "mouse_click",
      "data": {
        "x": 1533,
        "y": 270,
        "button": "Button.left",
        "pressed": true
      },
      "delay_after": 0.0
    },
    {
      "timestamp": 7.9066481590271,
      "action_type": "mouse_click",
      "data": {
        "x": 1533,
        "y": 270,
        "button": "Button.left",
        "pressed": false
      },
      "delay_after": 0.0
    }
  ]
}